sortpuzsolver/__init__.py
sortpuzsolver/colorseg/__init__.py
sortpuzsolver/colorseg/colorsegmentor.py
sortpuzsolver/puzzlesolve/__init__.py
sortpuzsolver/puzzlesolve/recog/__init__.py
sortpuzsolver/puzzlesolve/recog/recog.py
sortpuzsolver/puzzlesolve/solver/__init__.py
sortpuzsolver/puzzlesolve/solver/main.cpp
sortpuzsolver/puzzlesolve/solver/main.exe
sortpuzsolver/puzzlesolve/solver/main.o
sortpuzsolver/puzzlesolve/solver/puzzlesolvelib.h
sortpuzsolver/puzzlesolve/solver/PuzzleSort.exe
sortpuzsolver/puzzlesolve/solver/puzzlesortsolver.py
sortpuzsolver-0.1.4.dist-info/LICENSE
sortpuzsolver-0.1.4.dist-info/METADATA
sortpuzsolver-0.1.4.dist-info/WHEEL
sortpuzsolver-0.1.4.dist-info/RECORD
