Metadata-Version: 2.1
Name: sortpuzsolver
Version: 0.1.4
Summary: Solves sorting puzzles.
License: MIT
Author: Kameren Clark
Author-email: clarkkameren@gmail.com
Requires-Python: >=3.10,<4.0
Classifier: License :: OSI Approved :: MIT License
Classifier: Programming Language :: Python :: 3
Classifier: Programming Language :: Python :: 3.10
Classifier: Programming Language :: Python :: 3.11
Classifier: Programming Language :: Python :: 3.12
Requires-Dist: matplotlib (>=3.9.2,<4.0.0)
Requires-Dist: opencv-contrib-python-headless (>=4.10.0.84,<5.0.0.0)
Requires-Dist: scikit-image (>=0.24.0,<0.25.0)
Requires-Dist: scipy (>=1.14.0,<2.0.0)
